{
  "generated_at": "2026-05-30 18:01:01",
  "trade_date": "2026-05-29",
  "market_score": 60,
  "holding_days": 1,
  "hold_plan": "T 日收盘确认信号并以收盘价买入 → T+1 用最低价模拟 -3% 硬止损 → 未触发则 T+1 收盘平仓",
  "sell_offset": 1,
  "stop_loss_ratio": 0.03,
  "count": 5,
  "signals": [
    {
      "股票代码": "600549",
      "股票名称": "厦门钨业",
      "信号日": "2026-05-29",
      "收盘价": "54.37 元",
      "日涨幅": "3.76%",
      "五日量比": "1.64 倍",
      "KDJ_J": 80.26,
      "MACD柱": 0.0291,
      "规则得分": 79.67,
      "持仓计划": "T 日收盘确认信号并以收盘价买入 → T+1 用最低价模拟 -3% 硬止损 → 未触发则 T+1 收盘平仓",
      "实盘建议": "✅ 短线共振成立：T 日收盘买入，T+1 用日线最低价评估 -3% 止损"
    },
    {
      "股票代码": "600729",
      "股票名称": "重百集团",
      "信号日": "2026-05-29",
      "收盘价": "20.05 元",
      "日涨幅": "5.86%",
      "五日量比": "2.13 倍",
      "KDJ_J": 68.48,
      "MACD柱": 0.0362,
      "规则得分": 79.41,
      "持仓计划": "T 日收盘确认信号并以收盘价买入 → T+1 用最低价模拟 -3% 硬止损 → 未触发则 T+1 收盘平仓",
      "实盘建议": "✅ 短线共振成立：T 日收盘买入，T+1 用日线最低价评估 -3% 止损"
    },
    {
      "股票代码": "600593",
      "股票名称": "大连圣亚",
      "信号日": "2026-05-29",
      "收盘价": "37.60 元",
      "日涨幅": "4.47%",
      "五日量比": "1.57 倍",
      "KDJ_J": 85.35,
      "MACD柱": 0.6821,
      "规则得分": 75.17,
      "持仓计划": "T 日收盘确认信号并以收盘价买入 → T+1 用最低价模拟 -3% 硬止损 → 未触发则 T+1 收盘平仓",
      "实盘建议": "✅ 短线共振成立：T 日收盘买入，T+1 用日线最低价评估 -3% 止损"
    },
    {
      "股票代码": "000402",
      "股票名称": "金 融 街",
      "信号日": "2026-05-29",
      "收盘价": "3.09 元",
      "日涨幅": "5.46%",
      "五日量比": "2.41 倍",
      "KDJ_J": 62.11,
      "MACD柱": -0.0403,
      "规则得分": 73.76,
      "持仓计划": "T 日收盘确认信号并以收盘价买入 → T+1 用最低价模拟 -3% 硬止损 → 未触发则 T+1 收盘平仓",
      "实盘建议": "✅ 短线共振成立：T 日收盘买入，T+1 用日线最低价评估 -3% 止损"
    },
    {
      "股票代码": "600505",
      "股票名称": "西昌电力",
      "信号日": "2026-05-29",
      "收盘价": "13.42 元",
      "日涨幅": "2.76%",
      "五日量比": "1.71 倍",
      "KDJ_J": 82.39,
      "MACD柱": 0.0015,
      "规则得分": 72.81,
      "持仓计划": "T 日收盘确认信号并以收盘价买入 → T+1 用最低价模拟 -3% 硬止损 → 未触发则 T+1 收盘平仓",
      "实盘建议": "✅ 短线共振成立：T 日收盘买入，T+1 用日线最低价评估 -3% 止损"
    }
  ],
  "orders": [
    {
      "order_id": 171,
      "stock_code": "600549",
      "stock_name": "厦门钨业",
      "buy_date": "2026-05-29",
      "buy_price": 54.37,
      "sell_date": null,
      "sell_price": null,
      "hold_days": 0,
      "pnl_ratio": null,
      "status": "HOLDING",
      "stop_loss_triggered": 0,
      "signal_rank": 1,
      "rule_score": 79.66940339725319,
      "exit_reason": "await_t1_kline"
    },
    {
      "order_id": 172,
      "stock_code": "600729",
      "stock_name": "重百集团",
      "buy_date": "2026-05-29",
      "buy_price": 20.05,
      "sell_date": null,
      "sell_price": null,
      "hold_days": 0,
      "pnl_ratio": null,
      "status": "HOLDING",
      "stop_loss_triggered": 0,
      "signal_rank": 2,
      "rule_score": 79.41307620594606,
      "exit_reason": "await_t1_kline"
    },
    {
      "order_id": 173,
      "stock_code": "600593",
      "stock_name": "大连圣亚",
      "buy_date": "2026-05-29",
      "buy_price": 37.6,
      "sell_date": null,
      "sell_price": null,
      "hold_days": 0,
      "pnl_ratio": null,
      "status": "HOLDING",
      "stop_loss_triggered": 0,
      "signal_rank": 3,
      "rule_score": 75.17129239615129,
      "exit_reason": "await_t1_kline"
    },
    {
      "order_id": 174,
      "stock_code": "000402",
      "stock_name": "金 融 街",
      "buy_date": "2026-05-29",
      "buy_price": 3.09,
      "sell_date": null,
      "sell_price": null,
      "hold_days": 0,
      "pnl_ratio": null,
      "status": "HOLDING",
      "stop_loss_triggered": 0,
      "signal_rank": 4,
      "rule_score": 73.76377805564891,
      "exit_reason": "await_t1_kline"
    },
    {
      "order_id": 175,
      "stock_code": "600505",
      "stock_name": "西昌电力",
      "buy_date": "2026-05-29",
      "buy_price": 13.42,
      "sell_date": null,
      "sell_price": null,
      "hold_days": 0,
      "pnl_ratio": null,
      "status": "HOLDING",
      "stop_loss_triggered": 0,
      "signal_rank": 5,
      "rule_score": 72.80600368859702,
      "exit_reason": "await_t1_kline"
    }
  ],
  "execution": {
    "buy_date": "2026-05-29",
    "orders": [
      {
        "stock_code": "600549",
        "stock_name": "厦门钨业",
        "buy_date": "2026-05-29",
        "buy_price": 54.37,
        "sell_date": null,
        "sell_price": null,
        "hold_days": 0,
        "pnl_ratio": null,
        "status": "HOLDING",
        "stop_loss_triggered": 0,
        "rank": 1,
        "rule_score": 79.66940339725319,
        "exit_reason": "await_t1_kline",
        "hold_plan": "T 日收盘确认信号并以收盘价买入 → T+1 用最低价模拟 -3% 硬止损 → 未触发则 T+1 收盘平仓",
        "t1_open": null,
        "t1_low": null,
        "t1_close": null,
        "t2_open": null,
        "t2_close": null,
        "stop_loss_price": 52.738899999999994
      },
      {
        "stock_code": "600729",
        "stock_name": "重百集团",
        "buy_date": "2026-05-29",
        "buy_price": 20.05,
        "sell_date": null,
        "sell_price": null,
        "hold_days": 0,
        "pnl_ratio": null,
        "status": "HOLDING",
        "stop_loss_triggered": 0,
        "rank": 2,
        "rule_score": 79.41307620594606,
        "exit_reason": "await_t1_kline",
        "hold_plan": "T 日收盘确认信号并以收盘价买入 → T+1 用最低价模拟 -3% 硬止损 → 未触发则 T+1 收盘平仓",
        "t1_open": null,
        "t1_low": null,
        "t1_close": null,
        "t2_open": null,
        "t2_close": null,
        "stop_loss_price": 19.4485
      },
      {
        "stock_code": "600593",
        "stock_name": "大连圣亚",
        "buy_date": "2026-05-29",
        "buy_price": 37.6,
        "sell_date": null,
        "sell_price": null,
        "hold_days": 0,
        "pnl_ratio": null,
        "status": "HOLDING",
        "stop_loss_triggered": 0,
        "rank": 3,
        "rule_score": 75.17129239615129,
        "exit_reason": "await_t1_kline",
        "hold_plan": "T 日收盘确认信号并以收盘价买入 → T+1 用最低价模拟 -3% 硬止损 → 未触发则 T+1 收盘平仓",
        "t1_open": null,
        "t1_low": null,
        "t1_close": null,
        "t2_open": null,
        "t2_close": null,
        "stop_loss_price": 36.472
      },
      {
        "stock_code": "000402",
        "stock_name": "金 融 街",
        "buy_date": "2026-05-29",
        "buy_price": 3.09,
        "sell_date": null,
        "sell_price": null,
        "hold_days": 0,
        "pnl_ratio": null,
        "status": "HOLDING",
        "stop_loss_triggered": 0,
        "rank": 4,
        "rule_score": 73.76377805564891,
        "exit_reason": "await_t1_kline",
        "hold_plan": "T 日收盘确认信号并以收盘价买入 → T+1 用最低价模拟 -3% 硬止损 → 未触发则 T+1 收盘平仓",
        "t1_open": null,
        "t1_low": null,
        "t1_close": null,
        "t2_open": null,
        "t2_close": null,
        "stop_loss_price": 2.9972999999999996
      },
      {
        "stock_code": "600505",
        "stock_name": "西昌电力",
        "buy_date": "2026-05-29",
        "buy_price": 13.42,
        "sell_date": null,
        "sell_price": null,
        "hold_days": 0,
        "pnl_ratio": null,
        "status": "HOLDING",
        "stop_loss_triggered": 0,
        "rank": 5,
        "rule_score": 72.80600368859702,
        "exit_reason": "await_t1_kline",
        "hold_plan": "T 日收盘确认信号并以收盘价买入 → T+1 用最低价模拟 -3% 硬止损 → 未触发则 T+1 收盘平仓",
        "t1_open": null,
        "t1_low": null,
        "t1_close": null,
        "t2_open": null,
        "t2_close": null,
        "stop_loss_price": 13.0174
      }
    ],
    "closed_count": 0,
    "holding_count": 5,
    "stop_loss_count": 0
  }
}