{
  "start_date": "2025-05-09",
  "end_date": "2026-05-29",
  "scan_end_date": "2026-05-27",
  "top_n": 5,
  "sell_offset": 2,
  "stop_loss_ratio": 0.03,
  "close_stop_ratio": 0.05,
  "entry_max_chase": 0.01,
  "entry_min_gap": -0.02,
  "min_market_score": 60,
  "include_300": false,
  "include_688": false,
  "max_scan_stocks": null,
  "calendar_days_scanned": 255,
  "signal_days": 149,
  "fused_days": 73,
  "empty_days": 33,
  "total_trades": 785,
  "closed_trades": 614,
  "holding_trades": 0,
  "skipped_trades": 171,
  "win_rate": 0.44299674267100975,
  "avg_pnl_pct": 0.2419683992865769,
  "median_pnl_pct": -0.20089830450850968,
  "cum_return_pct": 61.58458818957821,
  "max_drawdown_pct": -7.147112617504847,
  "exit_reason_counts": {
    "t1_mediocre_close_exit": 565,
    "t1_intraday_take_profit": 39,
    "t2_close_exit": 5,
    "t2_trend_ride_exit": 3,
    "t1_close_below_stop_limit": 2
  }
}